MANIFEST.in
README.rst
TODO.txt
VERSION.txt
setup.cfg
setup.py
passwordmeter/__init__.py
passwordmeter/cli.py
passwordmeter/i18n.py
passwordmeter/test_passwordmeter.py
passwordmeter.egg-info/PKG-INFO
passwordmeter.egg-info/SOURCES.txt
passwordmeter.egg-info/dependency_links.txt
passwordmeter.egg-info/entry_points.txt
passwordmeter.egg-info/requires.txt
passwordmeter.egg-info/top_level.txt
passwordmeter.egg-info/zip-safe
passwordmeter/res/common.txt